{"cameraMode":{"drawMode":0,"name":"Shaded","section":"Shading Mode"},"sceneLighting":true,"audioPlay":false,"sceneViewState":{"showFog":true,"showMaterialUpdate":false,"showSkybox":true,"showFlares":true,"showImageEffects":true,"showParticleSystems":true},"in2DMode":false,"pivot":{"x":-0.0395941287279129,"y":-0.9676746129989624,"z":-19.91823959350586},"rotation":{"x":0.007167387753725052,"y":0.9811496138572693,"z":-0.18951831758022309,"w":0.03710610419511795},"size":3.1001782417297365,"orthographic":false}